globalprocessing_client/__init__.py
globalprocessing_client/client.py
globalprocessing_client/exceptions.py
Global_Processing_Services_Client-0.0.1.dist-info/LICENSE
Global_Processing_Services_Client-0.0.1.dist-info/METADATA
Global_Processing_Services_Client-0.0.1.dist-info/WHEEL
Global_Processing_Services_Client-0.0.1.dist-info/top_level.txt
Global_Processing_Services_Client-0.0.1.dist-info/RECORD
