Metadata-Version: 2.1
Name: Global-Processing-Services-Client
Version: 0.0.1
Summary: Client library for Global Processing Services
Home-page: https://github.com/divipayhq/py-gps-client
Author: Hammy Goonan
Author-email: hammy@divipay.com
License: MIT
Platform: UNKNOWN
Classifier: License :: OSI Approved :: MIT License
Classifier: Programming Language :: Python :: 3
Classifier: Programming Language :: Python :: 3 :: Only
Classifier: Programming Language :: Python :: 3.9
Classifier: Programming Language :: Python :: Implementation :: CPython
Requires-Python: >=3.8
License-File: LICENSE
Requires-Dist: zeep (~=4.1.0)
Requires-Dist: pytz (==2022.1)
